connector/__init__.py
connector/_version.py
connector/cli.py
connector/googlecloud.py
connector/googledrive.py
connector/init_conda_env.py
connector/remote.py
connector/restricted.py
teamconnector-0.1.10.dist-info/LICENSE.md
teamconnector-0.1.10.dist-info/METADATA
teamconnector-0.1.10.dist-info/WHEEL
teamconnector-0.1.10.dist-info/entry_points.txt
teamconnector-0.1.10.dist-info/top_level.txt
teamconnector-0.1.10.dist-info/RECORD
